{"BaseModel.76a2d825-4fa3-45d3-826b-26bbd33c2a07": {"id": "76a2d825-4fa3-45d3-826b-26bbd33c2a07", "created_at": "2023-11-21T19:02:20.702731", "updated_at": "2023-11-21T19:02:20.702746", "__class__": "BaseModel"}, "BaseModel.a4a0fb7e-1eb1-4122-b43c-51b87baa542a": {"id": "a4a0fb7e-1eb1-4122-b43c-51b87baa542a", "created_at": "2023-11-21T18:59:55.800119", "updated_at": "2023-11-21T18:59:55.800136", "__class__": "BaseModel"}, "BaseModel.14e37ac2-a9f6-4957-9e12-09814aafbbbd": {"id": "14e37ac2-a9f6-4957-9e12-09814aafbbbd", "created_at": "2023-11-21T18:46:49.240168", "updated_at": "2023-11-21T18:46:49.240190", "__class__": "BaseModel"}, "State.1230e877-774b-4016-b2bb-657fa96ce7cb": {"id": "1230e877-774b-4016-b2bb-657fa96ce7cb", "created_at": "2023-11-21T18:46:50.951281", "updated_at": "2023-11-21T18:46:50.951305", "name": "California", "__class__": "State"}, "Place.d9e215b6-bc27-4480-ae4d-17a8085b7d6d": {"id": "d9e215b6-bc27-4480-ae4d-17a8085b7d6d", "created_at": "2023-11-21T18:47:24.270808", "updated_at": "2023-11-21T18:47:24.270821", "city_id": "0001", "user_id": "0001", "name": "My little house", "number_rooms": 4, "number_bathrooms": 2, "max_guest": 10, "price_by_night": 300, "latitude": 37.773972, "longitude": -122.431297, "__class__": "Place"}, "State.e7ffef36-788d-4009-945c-f634ffd34109": {"id": "e7ffef36-788d-4009-945c-f634ffd34109", "created_at": "2023-11-21T19:00:13.781852", "updated_at": "2023-11-21T19:00:13.781876", "__class__": "State"}, "State.b6941994-7939-49a8-a54e-37624bfdc9ee": {"id": "b6941994-7939-49a8-a54e-37624bfdc9ee", "created_at": "2023-11-21T19:02:20.713693", "updated_at": "2023-11-21T19:02:20.713713", "name": "California", "__class__": "State"}, "State.f2c0b3e7-9910-4786-a711-df5ac755fc59": {"id": "f2c0b3e7-9910-4786-a711-df5ac755fc59", "created_at": "2023-11-21T19:02:20.715346", "updated_at": "2023-11-21T19:02:20.715360", "name": "Arizona", "__class__": "State"}, "Place.7bba08c0-dab7-461a-8f5d-818f22c6e64d": {"id": "7bba08c0-dab7-461a-8f5d-818f22c6e64d", "created_at": "2023-11-21T19:02:20.717283", "updated_at": "2023-11-21T19:02:20.717299", "city_id": "0001", "user_id": "0001", "name": "My little house", "number_rooms": 4, "number_bathrooms": 2, "max_guest": 10, "price_by_night": 300, "latitude": 37.773972, "longitude": -122.431297, "__class__": "Place"}}